jira_sro_etl/__init__.py
jira_sro_etl/base_entity.py
jira_sro_etl/development_task_type.py
jira_sro_etl/epic.py
jira_sro_etl/factories.py
jira_sro_etl/manager.py
jira_sro_etl/priority.py
jira_sro_etl/product_backlog.py
jira_sro_etl/scrum_development_task.py
jira_sro_etl/scrum_development_task_history.py
jira_sro_etl/scrum_development_team.py
jira_sro_etl/scrum_project.py
jira_sro_etl/scrum_project_team.py
jira_sro_etl/sprint.py
jira_sro_etl/sprint_backlog.py
jira_sro_etl/team_member.py
jira_sro_etl/user.py
jira_sro_etl/user_story.py
jira_sro_etl/conversor/__init__.py
jira_sro_etl/conversor/conversor.py
jira_sro_etl/conversor/conversor_developmentTeam.py
jira_sro_etl/conversor/conversor_epic.py
jira_sro_etl/conversor/conversor_project.py
jira_sro_etl/conversor/conversor_sprint.py
jira_sro_etl/conversor/conversor_task.py
jira_sro_etl/conversor/conversor_team.py
jira_sro_etl/conversor/conversor_teamMember.py
jira_sro_etl/conversor/conversor_user.py
jira_sro_etl/conversor/conversor_userStory.py
jira_sro_etl/conversor/factories.py
jira_sro_etl/mongo_db/__init__.py
jira_sro_etl/mongo_db/sro_mongo_db.py
jira_sro_etl-26.0.0.dist-info/METADATA
jira_sro_etl-26.0.0.dist-info/WHEEL
jira_sro_etl-26.0.0.dist-info/top_level.txt
jira_sro_etl-26.0.0.dist-info/RECORD
