Metadata-Version: 2.1
Name: jira-sro-etl
Version: 26.0.0
Summary: Library responsible for extracting data from Jira to SRO database
Home-page: https://gitlab.com/integration_seon/libs/etl/jira_sro_etl
Author: Leonardo Khoury Picoli, Lucas Moraes Soares de Souza, Paulo Sérgio dos Santos Júnior
Author-email: leonardokhoury@hotmail.com, lucasmoraesplay@gmail.com, paulossjunior@gmail.com
License: UNKNOWN
Platform: UNKNOWN
Classifier: Programming Language :: Python :: 3
Classifier: License :: OSI Approved :: MIT License
Classifier: Operating System :: OS Independent
Requires-Dist: behave
Requires-Dist: commitizen
Requires-Dist: factory-boy
